_foo.cpython-311-x86_64-linux-gnu.so
tfra_nightly_gpu-0.6.1.dev20240429223730.dist-info/RECORD
tfra_nightly_gpu-0.6.1.dev20240429223730.dist-info/METADATA
tfra_nightly_gpu-0.6.1.dev20240429223730.dist-info/WHEEL
tfra_nightly_gpu-0.6.1.dev20240429223730.dist-info/top_level.txt
tfra_nightly_gpu-0.6.1.dev20240429223730.dist-info/LICENSE
tensorflow_recommenders_addons/register.py
tensorflow_recommenders_addons/conftest.py
tensorflow_recommenders_addons/__init__.py
tensorflow_recommenders_addons/version.py
tensorflow_recommenders_addons/utils/ensure_tf_install.py
tensorflow_recommenders_addons/utils/test_utils.py
tensorflow_recommenders_addons/utils/check_platform.py
tensorflow_recommenders_addons/utils/__init__.py
tensorflow_recommenders_addons/utils/types.py
tensorflow_recommenders_addons/utils/resource_loader.py
tensorflow_recommenders_addons/dynamic_embedding/__init__.py
tensorflow_recommenders_addons/dynamic_embedding/core/_cuckoo_hashtable_ops.so
tensorflow_recommenders_addons/dynamic_embedding/core/_redis_table_ops.so
tensorflow_recommenders_addons/dynamic_embedding/core/_hkv_ops.so
tensorflow_recommenders_addons/dynamic_embedding/core/_data_flow_ops.so
tensorflow_recommenders_addons/dynamic_embedding/core/_math_ops.so
tensorflow_recommenders_addons/dynamic_embedding/python/__init__.py
tensorflow_recommenders_addons/dynamic_embedding/python/ops/shadow_embedding_ops.py
tensorflow_recommenders_addons/dynamic_embedding/python/ops/dynamic_embedding_variable.py
tensorflow_recommenders_addons/dynamic_embedding/python/ops/math_ops.py
tensorflow_recommenders_addons/dynamic_embedding/python/ops/redis_table_ops.py
tensorflow_recommenders_addons/dynamic_embedding/python/ops/ragged_embedding_ops.py
tensorflow_recommenders_addons/dynamic_embedding/python/ops/data_flow_grad.py
tensorflow_recommenders_addons/dynamic_embedding/python/ops/dynamic_embedding_creator.py
tensorflow_recommenders_addons/dynamic_embedding/python/ops/__init__.py
tensorflow_recommenders_addons/dynamic_embedding/python/ops/cuckoo_hashtable_ops.py
tensorflow_recommenders_addons/dynamic_embedding/python/ops/dynamic_embedding_optimizer.py
tensorflow_recommenders_addons/dynamic_embedding/python/ops/dynamic_embedding_ops.py
