Metadata-Version: 2.1
Name: tfra-nightly-gpu
Version: 0.6.1.dev20240429223730
Summary: TensorFlow Recommenders Addons.
Author: Google Inc.
Author-email: opensource@google.com
License: Apache 2.0
Keywords: tensorflow recommenders addons machine learning
Platform: UNKNOWN
Classifier: Development Status :: 4 - Beta
Classifier: Intended Audience :: Developers
Classifier: Intended Audience :: Education
Classifier: Intended Audience :: Science/Research
Classifier: License :: OSI Approved :: Apache Software License
Classifier: Programming Language :: Python :: 3
Classifier: Programming Language :: Python :: 3.9
Classifier: Programming Language :: Python :: 3.10
Classifier: Programming Language :: Python :: 3.11
Classifier: Topic :: Scientific/Engineering :: Mathematics
Classifier: Topic :: Software Development :: Libraries :: Python Modules
Classifier: Topic :: Software Development :: Libraries
License-File: LICENSE
Requires-Dist: tensorflow <=2.15.1,>=2.11.0
